tcn_sequence_models/__init__.py
tcn_sequence_models/models.py
tcn_sequence_models/data_processing/__init__.py
tcn_sequence_models/data_processing/gen_sequences.py
tcn_sequence_models/data_processing/preprocessing.py
tcn_sequence_models/data_processing/preprocessor.py
tcn_sequence_models/tf_models/__init__.py
tcn_sequence_models/tf_models/tcn.py
tcn_sequence_models/tf_models/tf_TCN_GRU/__init__.py
tcn_sequence_models/tf_models/tf_TCN_GRU/decoder.py
tcn_sequence_models/tf_models/tf_TCN_GRU/encoder.py
tcn_sequence_models/tf_models/tf_TCN_GRU/tcn_gru_attention_model.py
tcn_sequence_models/tf_models/tf_TCN_TCN_attention/__init__.py
tcn_sequence_models/tf_models/tf_TCN_TCN_attention/decoder.py
tcn_sequence_models/tf_models/tf_TCN_TCN_attention/encoder.py
tcn_sequence_models/tf_models/tf_TCN_TCN_attention/tcn_tcn_attention.py
tcn_sequence_models/tf_models/tf_TCN_TCN_normal/__init__.py
tcn_sequence_models/tf_models/tf_TCN_TCN_normal/decoder.py
tcn_sequence_models/tf_models/tf_TCN_TCN_normal/encoder.py
tcn_sequence_models/tf_models/tf_TCN_TCN_normal/tcn_tcn_normal.py
tcn_sequence_models/utils/__init__.py
tcn_sequence_models/utils/scaling.py
tcn_sequence_models/utils/train_test_split.py
tcn_sequence_models-0.0.8.dist-info/LICENSE
tcn_sequence_models-0.0.8.dist-info/METADATA
tcn_sequence_models-0.0.8.dist-info/WHEEL
tcn_sequence_models-0.0.8.dist-info/top_level.txt
tcn_sequence_models-0.0.8.dist-info/RECORD
