Metadata-Version: 2.1
Name: tcn-sequence-models
Version: 0.0.8
Summary: TCN based models for time series forecasting.
Home-page: https://github.com/Schichael/TCN_Seq2Seq
Author: Michael Schulten
Author-email: michael.schulten@yahoo.de
Classifier: Programming Language :: Python :: 3
Classifier: License :: OSI Approved :: MIT License
Classifier: Operating System :: OS Independent
Requires-Python: >=3.8
License-File: LICENSE
Requires-Dist: tensorflow (==2.5.0)
Requires-Dist: keras-tuner (==1.0.3)
Requires-Dist: tensorflow-addons (==0.13.0)
Requires-Dist: pandas (==1.2.4)
Requires-Dist: numpy (==1.19.2)
Requires-Dist: scikit-learn (==1.1.1)
Provides-Extra: dev
Requires-Dist: pytest ; extra == 'dev'
Provides-Extra: notebooks
Requires-Dist: matplotlib ; extra == 'notebooks'
Requires-Dist: jupyter ; extra == 'notebooks'
